azure/ai/agentserver/__init__.py
azure/ai/agentserver/langgraph/__init__.py
azure/ai/agentserver/langgraph/_version.py
azure/ai/agentserver/langgraph/langgraph.py
azure/ai/agentserver/langgraph/py.typed
azure/ai/agentserver/langgraph/tool_client.py
azure/ai/agentserver/langgraph/models/__init__.py
azure/ai/agentserver/langgraph/models/langgraph_request_converter.py
azure/ai/agentserver/langgraph/models/langgraph_response_converter.py
azure/ai/agentserver/langgraph/models/langgraph_state_converter.py
azure/ai/agentserver/langgraph/models/langgraph_stream_response_converter.py
azure/ai/agentserver/langgraph/models/utils.py
azure/ai/agentserver/langgraph/models/response_event_generators/__init__.py
azure/ai/agentserver/langgraph/models/response_event_generators/item_content_helpers.py
azure/ai/agentserver/langgraph/models/response_event_generators/item_resource_helpers.py
azure/ai/agentserver/langgraph/models/response_event_generators/response_content_part_event_generator.py
azure/ai/agentserver/langgraph/models/response_event_generators/response_event_generator.py
azure/ai/agentserver/langgraph/models/response_event_generators/response_function_call_argument_event_generator.py
azure/ai/agentserver/langgraph/models/response_event_generators/response_output_item_event_generator.py
azure/ai/agentserver/langgraph/models/response_event_generators/response_output_text_event_generator.py
azure/ai/agentserver/langgraph/models/response_event_generators/response_stream_event_generator.py
azure_ai_agentserver_langgraph-1.0.0b7.dist-info/licenses/LICENSE
azure_ai_agentserver_langgraph-1.0.0b7.dist-info/METADATA
azure_ai_agentserver_langgraph-1.0.0b7.dist-info/WHEEL
azure_ai_agentserver_langgraph-1.0.0b7.dist-info/top_level.txt
azure_ai_agentserver_langgraph-1.0.0b7.dist-info/RECORD
