Metadata-Version: 2.4
Name: azure-ai-agentserver-langgraph
Version: 1.0.0b7
Summary: LangGraph adapter for Azure AI Agent Server
Author-email: Microsoft Corporation <azpysdkhelp@microsoft.com>
License-Expression: MIT
Project-URL: repository, https://github.com/Azure/azure-sdk-for-python
Keywords: azure,azure sdk
Classifier: Programming Language :: Python
Classifier: Programming Language :: Python :: 3 :: Only
Classifier: Programming Language :: Python :: 3
Classifier: Programming Language :: Python :: 3.10
Classifier: Programming Language :: Python :: 3.11
Classifier: Programming Language :: Python :: 3.12
Classifier: Programming Language :: Python :: 3.13
Requires-Python: >=3.10
License-File: LICENSE
Requires-Dist: azure-ai-agentserver-core>=1.0.0b7
Requires-Dist: langchain>0.3.20
Requires-Dist: langchain-openai>0.3.10
Requires-Dist: langchain-azure-ai[opentelemetry]>=0.1.8
Dynamic: license-file
